getrest/__init__.py
getrest/api.py
getrest/authentication.py
getrest/exceptions.py
getrest/utils.py
getrest-0.2.2.dist-info/METADATA
getrest-0.2.2.dist-info/RECORD
getrest-0.2.2.dist-info/WHEEL
getrest-0.2.2.dist-info/top_level.txt
getrest-0.2.2.dist-info/zip-safe
