Metadata-Version: 2.1
Name: getrest
Version: 0.2.2
Summary: Rest client for projects that consume data
Home-page: http://gitlab.com/melvyn-sopacua/getrest
Author: Melvyn Sopacua
Author-email: m.r.sopacua@gmail.com
License: BSD 2-Clause License
Requires-Dist: requests (>=2.18)
Requires-Dist: urlobject (>=2.4)
Provides-Extra: docs
Requires-Dist: Sphinx (>=1.6); extra == 'docs'
Requires-Dist: sphinx-rtd-theme; extra == 'docs'
